PolymerPlotting/GUI_tools.py
PolymerPlotting/PolymerPlottingGUI.py
PolymerPlotting/__init__.py
PolymerPlotting/polymer_chains.py
PolymerPlotting-0.0.3.dist-info/LICENSE
PolymerPlotting-0.0.3.dist-info/METADATA
PolymerPlotting-0.0.3.dist-info/WHEEL
PolymerPlotting-0.0.3.dist-info/top_level.txt
PolymerPlotting-0.0.3.dist-info/RECORD
