Metadata-Version: 2.1
Name: PolymerPlotting
Version: 0.0.3
Summary: A package to create a GUI to plot models of polymer chains
Home-page: https://github.com/cnswoolley10/Polymer-Plotting
Author: Chris Woolley
Author-email: cnsw2@cam.ac.uk
License: UNKNOWN
Project-URL: Bug Tracker, https://github.com/cnswoolley10/Polymer-Plotting/issues
Platform: UNKNOWN
Classifier: Programming Language :: Python :: 3
Classifier: License :: OSI Approved :: MIT License
Classifier: Operating System :: OS Independent
Requires-Python: >=3.6
License-File: LICENSE
Requires-Dist: numpy
Requires-Dist: matplotlib
Requires-Dist: pysimplegui
